fds/__init__.py
fds/sdk/__init__.py
fds/sdk/OpenFactSetPartnersDocuments/__init__.py
fds/sdk/OpenFactSetPartnersDocuments/api_client.py
fds/sdk/OpenFactSetPartnersDocuments/configuration.py
fds/sdk/OpenFactSetPartnersDocuments/exceptions.py
fds/sdk/OpenFactSetPartnersDocuments/model_utils.py
fds/sdk/OpenFactSetPartnersDocuments/rest.py
fds/sdk/OpenFactSetPartnersDocuments/api/__init__.py
fds/sdk/OpenFactSetPartnersDocuments/api/link_up_api.py
fds/sdk/OpenFactSetPartnersDocuments/api/luxembourg_api.py
fds/sdk/OpenFactSetPartnersDocuments/api/orbit_api.py
fds/sdk/OpenFactSetPartnersDocuments/api/ozmosi_api.py
fds/sdk/OpenFactSetPartnersDocuments/api/scripts_asia_api.py
fds/sdk/OpenFactSetPartnersDocuments/apis/__init__.py
fds/sdk/OpenFactSetPartnersDocuments/model/__init__.py
fds/sdk/OpenFactSetPartnersDocuments/model/auth_status.py
fds/sdk/OpenFactSetPartnersDocuments/model/beam_endpoints_files.py
fds/sdk/OpenFactSetPartnersDocuments/model/beam_endpoints_response.py
fds/sdk/OpenFactSetPartnersDocuments/model/biomarkers_files.py
fds/sdk/OpenFactSetPartnersDocuments/model/biomarkers_response.py
fds/sdk/OpenFactSetPartnersDocuments/model/bonds.py
fds/sdk/OpenFactSetPartnersDocuments/model/collaborators_files.py
fds/sdk/OpenFactSetPartnersDocuments/model/collaborators_response.py
fds/sdk/OpenFactSetPartnersDocuments/model/data_files.py
fds/sdk/OpenFactSetPartnersDocuments/model/data_response.py
fds/sdk/OpenFactSetPartnersDocuments/model/diseases_files.py
fds/sdk/OpenFactSetPartnersDocuments/model/diseases_response.py
fds/sdk/OpenFactSetPartnersDocuments/model/error_example.py
fds/sdk/OpenFactSetPartnersDocuments/model/full_history_files.py
fds/sdk/OpenFactSetPartnersDocuments/model/full_history_response.py
fds/sdk/OpenFactSetPartnersDocuments/model/intervention_files.py
fds/sdk/OpenFactSetPartnersDocuments/model/intervention_response.py
fds/sdk/OpenFactSetPartnersDocuments/model/link_up_response.py
fds/sdk/OpenFactSetPartnersDocuments/model/linkup_files.py
fds.sdk.OpenFactSetPartnersDocuments-3.0.11.dist-info/LICENSE
fds.sdk.OpenFactSetPartnersDocuments-3.0.11.dist-info/METADATA
fds.sdk.OpenFactSetPartnersDocuments-3.0.11.dist-info/WHEEL
fds.sdk.OpenFactSetPartnersDocuments-3.0.11.dist-info/top_level.txt
fds.sdk.OpenFactSetPartnersDocuments-3.0.11.dist-info/RECORD
